{
   "ContextClassName": "ContosoUniversityContext",
   "ContextNamespace": null,
   "DefaultDacpacSchema": null,
   "FilterSchemas": false,
   "IncludeConnectionString": false,
   "ModelNamespace": null,
   "OutputContextPath": "Models",
   "OutputPath": "Models",
   "ProjectRootNamespace": "WebApplication4",
   "Schemas": null,
   "SelectedHandlebarsLanguage": 0,
   "SelectedToBeGenerated": 0,
   "Tables": [
      {
         "HasPrimaryKey": true,
         "Name": "[dbo].[Course]",
         "ObjectType": 0
      },
      {
         "HasPrimaryKey": true,
         "Name": "[dbo].[CourseInstructor]",
         "ObjectType": 0
      },
      {
         "HasPrimaryKey": true,
         "Name": "[dbo].[Department]",
         "ObjectType": 0
      },
      {
         "HasPrimaryKey": true,
         "Name": "[dbo].[Enrollment]",
         "ObjectType": 0
      },
      {
         "HasPrimaryKey": true,
         "Name": "[dbo].[OfficeAssignment]",
         "ObjectType": 0
      },
      {
         "HasPrimaryKey": true,
         "Name": "[dbo].[Person]",
         "ObjectType": 0
      },
      {
         "HasPrimaryKey": true,
         "Name": "[dbo].[vwCourseStudentCount]",
         "ObjectType": 0
      },
      {
         "HasPrimaryKey": true,
         "Name": "[dbo].[vwCourseStudents]",
         "ObjectType": 0
      },
      {
         "HasPrimaryKey": true,
         "Name": "[dbo].[vwDepartmentCourseCount]",
         "ObjectType": 0
      },
      {
         "HasPrimaryKey": true,
         "Name": "[dbo].[Department_Delete]",
         "ObjectType": 1
      },
      {
         "HasPrimaryKey": true,
         "Name": "[dbo].[Department_Insert]",
         "ObjectType": 1
      },
      {
         "HasPrimaryKey": true,
         "Name": "[dbo].[Department_Update]",
         "ObjectType": 1
      },
      {
         "HasPrimaryKey": true,
         "Name": "[dbo].[GetCourseReport]",
         "ObjectType": 1
      },
      {
         "HasPrimaryKey": true,
         "Name": "[dbo].[sp_alterdiagram]",
         "ObjectType": 1
      },
      {
         "HasPrimaryKey": true,
         "Name": "[dbo].[sp_creatediagram]",
         "ObjectType": 1
      },
      {
         "HasPrimaryKey": true,
         "Name": "[dbo].[sp_dropdiagram]",
         "ObjectType": 1
      },
      {
         "HasPrimaryKey": true,
         "Name": "[dbo].[sp_helpdiagramdefinition]",
         "ObjectType": 1
      },
      {
         "HasPrimaryKey": true,
         "Name": "[dbo].[sp_helpdiagrams]",
         "ObjectType": 1
      },
      {
         "HasPrimaryKey": true,
         "Name": "[dbo].[sp_renamediagram]",
         "ObjectType": 1
      },
      {
         "HasPrimaryKey": true,
         "Name": "[dbo].[sp_upgraddiagrams]",
         "ObjectType": 1
      }
   ],
   "UseDatabaseNames": false,
   "UseDbContextSplitting": false,
   "UseFluentApiOnly": true,
   "UseHandleBars": false,
   "UseInflector": true,
   "UseLegacyPluralizer": false,
   "UseNodaTime": false,
   "UseSpatial": false
}